streamrproxyclient/__init__.py
streamrproxyclient/libstreamrproxyclient.py
libstreamrproxyclient-2.0.5.dist-info/METADATA
libstreamrproxyclient-2.0.5.dist-info/WHEEL
libstreamrproxyclient-2.0.5.dist-info/licenses/LICENSE.txt
libstreamrproxyclient-2.0.5.dist-info/RECORD
