Metadata-Version: 2.4
Name: libstreamrproxyclient
Version: 2.0.5
Summary: Python bindings for libstreamrproxyclient
Project-URL: Homepage, https://github.com/streamr-dev/native-sdk
Project-URL: Documentation, https://github.com/streamr-dev/native-sdk/tree/main/wrappers/python
Project-URL: Repository, https://github.com/streamr-dev/native-sdk.git
Author-email: Petri Savolainen <petri.savolainen@streamr.network>
Maintainer-email: Petri Savolainen <petri.savolainen@streamr.network>
License-File: LICENSE.txt
Keywords: client,proxy,streamr
Classifier: Development Status :: 4 - Beta
Classifier: Programming Language :: Python
Requires-Python: >=3.12
